dbos_crewai/__init__.py
dbos_crewai/dbos_agent.py
dbos_crewai/dbos_agent_executor.py
dbos_crewai/dbos_llm.py
dbos_crewai/dbos_utils.py
dbos_crewai-0.0.2.dist-info/METADATA
dbos_crewai-0.0.2.dist-info/WHEEL
dbos_crewai-0.0.2.dist-info/licenses/LICENSE
dbos_crewai-0.0.2.dist-info/RECORD
