Metadata-Version: 2.4
Name: dbos-crewai
Version: 0.0.2
Summary: CrewAI DBOS durable agent
Project-URL: Homepage, https://dbos.dev
Project-URL: Source, https://github.com/dbos-inc/dbos-crewai
Project-URL: Documentation, https://docs.dbos.dev
Author-email: Qian Li <qian.li@dbos.dev>
License-Expression: MIT
License-File: LICENSE
Requires-Python: >=3.10
Requires-Dist: crewai>=1.3.0
Requires-Dist: dbos>=2.3.0
